README.md
setup.py
app_relation_net_graph/__init__.py
app_relation_net_graph/console.py
app_relation_net_graph.egg-info/PKG-INFO
app_relation_net_graph.egg-info/SOURCES.txt
app_relation_net_graph.egg-info/dependency_links.txt
app_relation_net_graph.egg-info/entry_points.txt
app_relation_net_graph.egg-info/not-zip-safe
app_relation_net_graph.egg-info/requires.txt
app_relation_net_graph.egg-info/top_level.txt
app_relation_net_graph/conf/__init__.py
app_relation_net_graph/conf/config.xml
app_relation_net_graph/conf/graph_config.xml
app_relation_net_graph/i18n/__init__.py
app_relation_net_graph/i18n/message_zh_cn.json
app_relation_net_graph/lib/__init__.py
app_relation_net_graph/lib/appnet_cmd.py