Metadata-Version: 1.2
Name: app-relation-net-graph
Version: 0.1.0
Summary: A command line tool for generate a graph of application relation net.
Home-page: https://github.com/snakeclub/app_relation_net_graph
Author: 黎慧剑
Author-email: snakeclub@163.com
Maintainer: 黎慧剑
Maintainer-email: snakeclub@163.com
License: Mozilla Public License 2.0
Keywords: Application Relation Net Graph
Platform: all
Classifier: Operating System :: OS Independent
Classifier: License :: OSI Approved :: Mozilla Public License 2.0 (MPL 2.0)
Classifier: Programming Language :: Python :: 3.6
Classifier: Topic :: Software Development :: Libraries
